MANIFEST.in
README.md
setup.cfg
setup.py
Comrade.egg-info/PKG-INFO
Comrade.egg-info/SOURCES.txt
Comrade.egg-info/dependency_links.txt
Comrade.egg-info/entry_points.txt
Comrade.egg-info/requires.txt
Comrade.egg-info/top_level.txt
comrade/__init__.py
comrade/command_line.py
comrade/configuration.py
comrade/executor.py
comrade/main_menu.py
comrade/utils.py
comrade/configs/sample_config.json
comrade/configs/test_config.json