Metadata-Version: 1.2
Name: Comrade
Version: 0.0.4
Summary: configurable command line tool
Home-page: https://github.com/erikmhauck/comrade
Author: Erik Hauck
Author-email: UNKNOWN
License: MIT
Project-URL: Documentation, https://github.com/erikmhauck/comrade
Project-URL: Source, https://github.com/erikmhauck/comrade
Project-URL: Tracker, https://github.com/erikmhauck/comrade/issues
Keywords: command line wrapper configurable tool
Platform: UNKNOWN
Classifier: Development Status :: 5 - Production/Stable
Classifier: Intended Audience :: End Users/Desktop
Classifier: Topic :: Utilities
Classifier: License :: OSI Approved :: MIT License
Classifier: Programming Language :: Python :: 2.7
Classifier: Programming Language :: Python :: 3
Classifier: Programming Language :: Python :: 3.2
Classifier: Programming Language :: Python :: 3.3
Classifier: Programming Language :: Python :: 3.4
Classifier: Programming Language :: Python :: 3.5
Classifier: Programming Language :: Python :: 3.6
Requires-Python: >=2.7, <4
